{
    "name": "PAINTRAIN",
    "twitchUsername": "blazingEmblem",
    "appearance": {
        "build": {
            "name": "tall-male",
            "gender": "Male",
            "buildValue": 1,
            "genderValue": 0
        },
        "face": 6,
        "hairstyle": 8,
        "hairDecoration": 0,
        "facialDetail": 2,
        "hairColor": {
            "value": "22",
            "hex": "#e85d64"
        },
        "voice": {
            "name": "Mature (Lower)",
            "id": 2
        },
        "accessories": {
            "head": null,
            "face": null,
            "arm": null,
            "body": {
                "id": 83,
                "name": "Tank Engine"
            }
        }
    },
    "stats": {
        "boon": {
            "name": "Mag",
            "id": 3
        },
        "bane": {
            "name": "Def",
            "id": 7
        }
    },
    "classes": {
        "base": {
            "name": "Sky Knight",
            "id": 59
        },
        "promoted": {
            "name": "Falcon Knight",
            "id": 57
        }
    },
    "skills": {
        "personal1": {
            "name": "Rally Strength",
            "id": 16
        },
        "personal2": {
            "name": "Rally Magic",
            "id": 17
        }
    },
    "timestamp": "1_1_1_1"
}