{
    "name": "Scala",
    "twitchUsername": "Safenritharnix",
    "appearance": {
        "build": {
            "name": "tall-male",
            "gender": "Male",
            "buildValue": 1,
            "genderValue": 0
        },
        "face": 2,
        "hairstyle": 11,
        "hairDecoration": 0,
        "facialDetail": 4,
        "hairColor": {
            "value": "19",
            "hex": "#eeb1b1"
        },
        "voice": {
            "name": "Mature (Lower)",
            "id": 2
        },
        "accessories": {
            "head": null,
            "face": null,
            "arm": {
                "id": 5,
                "name": "Dragon Feather"
            },
            "body": null
        }
    },
    "stats": {
        "boon": {
            "name": "Mag",
            "id": 3
        },
        "bane": {
            "name": "Skl",
            "id": 4
        }
    },
    "classes": {
        "base": {
            "name": "Nohr Prince(ss)",
            "id": 3
        },
        "promoted": {
            "name": "Hoshido Noble",
            "id": 5
        }
    },
    "skills": {
        "personal1": {
            "name": "Live to Serve",
            "id": 100
        },
        "personal2": {
            "name": "Amaterasu",
            "id": 97
        }
    },
    "timestamp": "1_1_1_1"
}