{
  "name": "Soter",
  "twitchUsername": "Dragontrainerguy2003",
  "appearance": {
    "build": {
      "name": "tall-male",
      "gender": "Male",
      "buildValue": 1,
      "genderValue": 0
    },
    "face": 4,
    "hairstyle": 4,
    "hairDecoration": 0,
    "facialDetail": 0,
    "hairColor": {
      "value": "custom",
      "hex": "#ce9ad6"
    },
    "voice": {
      "name": "jp-mature",
      "id": 6
    },
    "accessories": {
      "head": {
        "id": 65,
        "name": "Class Headwear"
      },
      "face": {
        "id": 66,
        "name": "Sunglasses"
      },
      "arm": null,
      "body": {
        "id": 84,
        "name": "Custom Outfit"
      }
    }
  },
  "stats": {
    "boon": {
      "name": "Mag",
      "id": 3
    },
    "bane": {
      "name": "Spd",
      "id": 5
    }
  },
  "classes": {
    "base": {
      "name": "Knight",
      "id": 13
    },
    "promoted": {
      "name": "General",
      "id": 15
    }
  },
  "skills": {
    "personal1": {
      "name": "Elbow Room",
      "id": 51
    },
    "personal2": {
      "name": "Malefic Aura",
      "id": 76
    }
  },
  "creationDate": "2_4_21_0"
}