{
  "name": "Barbara",
  "twitchUsername": "Ennatio",
  "appearance": {
    "build": {
      "name": "tall-female",
      "gender": "Female",
      "buildValue": 1,
      "genderValue": 1
    },
    "face": 6,
    "hairstyle": 8,
    "hairDecoration": 5,
    "facialDetail": 8,
    "hairColor": {
      "value": "24",
      "hex": "#e8db98"
    },
    "voice": {
      "name": "mute",
      "id": 255
    },
    "accessories": {
      "head": null,
      "face": null,
      "arm": null,
      "body": {
        "id": 139,
        "name": "Mitama Voice"
      }
    }
  },
  "stats": {
    "boon": {
      "name": "Str",
      "id": 2
    },
    "bane": {
      "name": "Mag",
      "id": 3
    }
  },
  "classes": {
    "base": {
      "name": "Wolfskin",
      "id": 96
    },
    "promoted": {
      "name": "Wolfssegner",
      "id": 98
    }
  },
  "skills": {
    "personal1": {
      "name": "Heartseeker",
      "id": 89
    },
    "personal2": {
      "name": "Poison Strike",
      "id": 101
    }
  },
  "creationDate": "3_15_19_37"
}