{
  "name": "Lucky Duck",
  "twitchUsername": "oats_245",
  "appearance": {
    "build": {
      "name": "tall-female",
      "gender": "Female",
      "buildValue": 1,
      "genderValue": 1
    },
    "face": 4,
    "hairstyle": 9,
    "hairDecoration": 2,
    "facialDetail": 0,
    "hairColor": {
      "value": "16",
      "hex": "#3c7986"
    },
    "voice": {
      "name": "older",
      "id": 2
    },
    "accessories": {
      "head": {
        "id": 81,
        "name": "Dark Diadem"
      },
      "face": null,
      "arm": {
        "id": 42,
        "name": "Nohr Pauldron"
      },
      "body": null
    }
  },
  "stats": {
    "boon": {
      "name": "Lck",
      "id": 6
    },
    "bane": {
      "name": "Mag",
      "id": 3
    }
  },
  "classes": {
    "base": {
      "name": "Wyvern Rider",
      "id": 70
    },
    "promoted": {
      "name": "Wyvern Lord",
      "id": 68
    }
  },
  "skills": {
    "personal1": {
      "name": "Luck +4",
      "id": 6
    },
    "personal2": {
      "name": "Good Fortune",
      "id": 91
    }
  },
  "creationDate": "2_9_15_18"
}