{
  "name": "Sally",
  "twitchUsername": "ossy2600",
  "appearance": {
    "build": {
      "name": "tall-female",
      "gender": "Female",
      "buildValue": 1,
      "genderValue": 1
    },
    "face": 3,
    "hairstyle": 0,
    "hairDecoration": 2,
    "facialDetail": 2,
    "hairColor": {
      "value": "12",
      "hex": "#9b4444"
    },
    "voice": {
      "name": "jp-calm",
      "id": 7
    },
    "accessories": {
      "head": {
        "id": 25,
        "name": "Chef Hat"
      },
      "face": {
        "id": 29,
        "name": "Round Glasses"
      },
      "arm": {
        "id": 47,
        "name": "Heart Pauldron"
      },
      "body": null
    }
  },
  "stats": {
    "boon": {
      "name": "Skl",
      "id": 4
    },
    "bane": {
      "name": "Str",
      "id": 2
    }
  },
  "classes": {
    "base": {
      "name": "Troubadour Demoiselle",
      "id": 92
    },
    "promoted": {
      "name": "Butler/Maid",
      "id": 94
    }
  },
  "skills": {
    "personal1": {
      "name": "Miracle",
      "id": 36
    },
    "personal2": {
      "name": "Amaterasu",
      "id": 97
    }
  },
  "creationDate": "2_9_19_37"
}