{
    "name": "Dean",
    "twitchUsername": "Gregster1998",
    "appearance": {
        "build": {
            "name": "tall-male",
            "gender": "Male",
            "buildValue": 1,
            "genderValue": 0
        },
        "face": 3,
        "hairstyle": 6,
        "hairDecoration": 0,
        "facialDetail": 0,
        "hairColor": {
            "value": "3",
            "hex": "#d38969"
        },
        "voice": {
            "name": "Teen (Mid)",
            "id": 1
        },
        "accessories": {
            "head": null,
            "face": null,
            "arm": null,
            "body": null
        }
    },
    "stats": {
        "boon": {
            "name": "Str",
            "id": 2
        },
        "bane": {
            "name": "Def",
            "id": 7
        }
    },
    "classes": {
        "base": {
            "name": "Fighter",
            "id": 19
        },
        "promoted": {
            "name": "Berserker",
            "id": 17
        }
    },
    "skills": {
        "personal1": {
            "name": "Vengeance",
            "id": 32
        },
        "personal2": {
            "name": "Death Blow",
            "id": 59
        }
    },
    "timestamp": "1_1_1_1"
}